{"version":1,"resource":"vscode-remote://wsl%2Bubuntu/home/devviking/ladingPage-GodWar/scss/_patterns.scss","entries":[{"id":"kjQo.scss","timestamp":1695354492837},{"id":"uLKA.scss","timestamp":1695354503197},{"id":"zbds.scss","timestamp":1695354609507},{"id":"OMsf.scss","timestamp":1695439844057},{"id":"xp3x.scss","timestamp":1695441110387},{"id":"8cv4.scss","timestamp":1695444988657},{"id":"SMsD.scss","timestamp":1695445009547},{"id":"RdAU.scss","timestamp":1695445024157},{"id":"HeUx.scss","timestamp":1695447503977},{"id":"9fW4.scss","timestamp":1695447614877},{"id":"ybnP.scss","timestamp":1695448100487},{"id":"uZL4.scss","timestamp":1695448121317},{"id":"12x1.scss","timestamp":1695448173967},{"id":"eFpX.scss","source":"undoRedo.source","timestamp":1695448368817}]}